{
    "format_version": "1.21.6",
    "credit": "Made with Blockbench",
    "parent": "kaleidoscope_cookery:meals/gui/root",
    "render_type": "minecraft:cutout",
    "texture_size": [
        32,
        32
    ],
    "textures": {
        "0": "kaleidoscope_cookery:block/meals/numbing_spicy_chicken",
        "particle": "kaleidoscope_cookery:block/meals/porcelain_plate"
    },
    "elements": [
        {
            "name": "bb_main2",
            "from": [
                4.25,
                2.9,
                3
            ],
            "to": [
                6.25,
                5.9,
                8
            ],
            "rotation": {
                "angle": 22.5,
                "axis": "y",
                "origin": [
                    5.25,
                    4.4,
                    6
                ]
            },
            "faces": {
                "north": {
                    "uv": [
                        1.5,
                        13,
                        2.5,
                        14.5
                    ],
                    "texture": "#0"
                },
                "east": {
                    "uv": [
                        1.5,
                        13,
                        4,
                        14.5
                    ],
                    "texture": "#0"
                },
                "south": {
                    "uv": [
                        1.5,
                        13,
                        2.5,
                        14.5
                    ],
                    "texture": "#0"
                },
                "west": {
                    "uv": [
                        1.5,
                        13,
                        4,
                        14.5
                    ],
                    "texture": "#0"
                },
                "up": {
                    "uv": [
                        1.5,
                        11.5,
                        4,
                        12.5
                    ],
                    "rotation": 90,
                    "texture": "#0"
                },
                "down": {
                    "uv": [
                        1.5,
                        13,
                        4,
                        14
                    ],
                    "rotation": 90,
                    "texture": "#0"
                }
            }
        },
        {
            "name": "bb_main2",
            "from": [
                7.25,
                2.9,
                3
            ],
            "to": [
                9.25,
                5.9,
                8
            ],
            "rotation": {
                "angle": 22.5,
                "axis": "y",
                "origin": [
                    8.25,
                    4.4,
                    6
                ]
            },
            "faces": {
                "north": {
                    "uv": [
                        1.5,
                        13,
                        2.5,
                        14.5
                    ],
                    "texture": "#0"
                },
                "east": {
                    "uv": [
                        1.5,
                        13,
                        4,
                        14.5
                    ],
                    "texture": "#0"
                },
                "south": {
                    "uv": [
                        1.5,
                        13,
                        2.5,
                        14.5
                    ],
                    "texture": "#0"
                },
                "west": {
                    "uv": [
                        1.5,
                        13,
                        4,
                        14.5
                    ],
                    "texture": "#0"
                },
                "up": {
                    "uv": [
                        1.5,
                        11.5,
                        4,
                        12.5
                    ],
                    "rotation": 90,
                    "texture": "#0"
                },
                "down": {
                    "uv": [
                        1.5,
                        13,
                        4,
                        14
                    ],
                    "rotation": 90,
                    "texture": "#0"
                }
            }
        },
        {
            "name": "bb_main2",
            "from": [
                10.25,
                2.9,
                3
            ],
            "to": [
                12.25,
                5.9,
                8
            ],
            "rotation": {
                "angle": 22.5,
                "axis": "y",
                "origin": [
                    11.25,
                    4.4,
                    6
                ]
            },
            "faces": {
                "north": {
                    "uv": [
                        1.5,
                        13,
                        2.5,
                        14.5
                    ],
                    "texture": "#0"
                },
                "east": {
                    "uv": [
                        1.5,
                        13,
                        4,
                        14.5
                    ],
                    "texture": "#0"
                },
                "south": {
                    "uv": [
                        1.5,
                        13,
                        2.5,
                        14.5
                    ],
                    "texture": "#0"
                },
                "west": {
                    "uv": [
                        1.5,
                        13,
                        4,
                        14.5
                    ],
                    "texture": "#0"
                },
                "up": {
                    "uv": [
                        1.5,
                        11.5,
                        4,
                        12.5
                    ],
                    "rotation": 90,
                    "texture": "#0"
                },
                "down": {
                    "uv": [
                        1.5,
                        13,
                        4,
                        14
                    ],
                    "rotation": 90,
                    "texture": "#0"
                }
            }
        },
        {
            "name": "bb_main2",
            "from": [
                4,
                3,
                7.75
            ],
            "to": [
                6,
                6,
                12.75
            ],
            "rotation": {
                "angle": 22.5,
                "axis": "y",
                "origin": [
                    5,
                    4.5,
                    10.75
                ]
            },
            "faces": {
                "north": {
                    "uv": [
                        1.5,
                        13,
                        2.5,
                        14.5
                    ],
                    "texture": "#0"
                },
                "east": {
                    "uv": [
                        1.5,
                        13,
                        4,
                        14.5
                    ],
                    "texture": "#0"
                },
                "south": {
                    "uv": [
                        1.5,
                        13,
                        2.5,
                        14.5
                    ],
                    "texture": "#0"
                },
                "west": {
                    "uv": [
                        1.5,
                        13,
                        4,
                        14.5
                    ],
                    "texture": "#0"
                },
                "up": {
                    "uv": [
                        1.5,
                        11.5,
                        4,
                        12.5
                    ],
                    "rotation": 90,
                    "texture": "#0"
                },
                "down": {
                    "uv": [
                        1.5,
                        13,
                        4,
                        14
                    ],
                    "rotation": 90,
                    "texture": "#0"
                }
            }
        },
        {
            "name": "bb_main2",
            "from": [
                7,
                3,
                7.75
            ],
            "to": [
                9,
                6,
                12.75
            ],
            "rotation": {
                "angle": 22.5,
                "axis": "y",
                "origin": [
                    8,
                    4.5,
                    10.75
                ]
            },
            "faces": {
                "north": {
                    "uv": [
                        1.5,
                        13,
                        2.5,
                        14.5
                    ],
                    "texture": "#0"
                },
                "east": {
                    "uv": [
                        1.5,
                        13,
                        4,
                        14.5
                    ],
                    "texture": "#0"
                },
                "south": {
                    "uv": [
                        1.5,
                        13,
                        2.5,
                        14.5
                    ],
                    "texture": "#0"
                },
                "west": {
                    "uv": [
                        1.5,
                        13,
                        4,
                        14.5
                    ],
                    "texture": "#0"
                },
                "up": {
                    "uv": [
                        1.5,
                        11.5,
                        4,
                        12.5
                    ],
                    "rotation": 90,
                    "texture": "#0"
                },
                "down": {
                    "uv": [
                        1.5,
                        13,
                        4,
                        14
                    ],
                    "rotation": 90,
                    "texture": "#0"
                }
            }
        },
        {
            "name": "bb_main2",
            "from": [
                10,
                3,
                7.75
            ],
            "to": [
                12,
                6,
                12.75
            ],
            "rotation": {
                "angle": 22.5,
                "axis": "y",
                "origin": [
                    11,
                    4.5,
                    10.75
                ]
            },
            "faces": {
                "north": {
                    "uv": [
                        1.5,
                        13,
                        2.5,
                        14.5
                    ],
                    "texture": "#0"
                },
                "east": {
                    "uv": [
                        1.5,
                        13,
                        4,
                        14.5
                    ],
                    "texture": "#0"
                },
                "south": {
                    "uv": [
                        1.5,
                        13,
                        2.5,
                        14.5
                    ],
                    "texture": "#0"
                },
                "west": {
                    "uv": [
                        1.5,
                        13,
                        4,
                        14.5
                    ],
                    "texture": "#0"
                },
                "up": {
                    "uv": [
                        1.5,
                        11.5,
                        4,
                        12.5
                    ],
                    "rotation": 90,
                    "texture": "#0"
                },
                "down": {
                    "uv": [
                        1.5,
                        13,
                        4,
                        14
                    ],
                    "rotation": 90,
                    "texture": "#0"
                }
            }
        },
        {
            "name": "bb_main2",
            "from": [
                6,
                2.75,
                6
            ],
            "to": [
                8,
                4.75,
                8
            ],
            "rotation": {
                "angle": 0,
                "axis": "y",
                "origin": [
                    8,
                    0,
                    8
                ]
            },
            "faces": {
                "north": {
                    "uv": [
                        9.5,
                        14.5,
                        10.5,
                        15.5
                    ],
                    "texture": "#0"
                },
                "east": {
                    "uv": [
                        9.5,
                        14.5,
                        10.5,
                        15.5
                    ],
                    "texture": "#0"
                },
                "south": {
                    "uv": [
                        9.5,
                        14.5,
                        10.5,
                        15.5
                    ],
                    "texture": "#0"
                },
                "west": {
                    "uv": [
                        9.5,
                        14.5,
                        10.5,
                        15.5
                    ],
                    "texture": "#0"
                },
                "up": {
                    "uv": [
                        9.5,
                        14.5,
                        10.5,
                        15.5
                    ],
                    "texture": "#0"
                },
                "down": {
                    "uv": [
                        9.5,
                        14.5,
                        10.5,
                        15.5
                    ],
                    "texture": "#0"
                }
            }
        },
        {
            "name": "bb_main2",
            "from": [
                11,
                3,
                10
            ],
            "to": [
                13,
                5,
                12
            ],
            "rotation": {
                "angle": 0,
                "axis": "y",
                "origin": [
                    8,
                    0,
                    8
                ]
            },
            "faces": {
                "north": {
                    "uv": [
                        9.5,
                        14.5,
                        10.5,
                        15.5
                    ],
                    "texture": "#0"
                },
                "east": {
                    "uv": [
                        9.5,
                        14.5,
                        10.5,
                        15.5
                    ],
                    "texture": "#0"
                },
                "south": {
                    "uv": [
                        9.5,
                        14.5,
                        10.5,
                        15.5
                    ],
                    "texture": "#0"
                },
                "west": {
                    "uv": [
                        9.5,
                        14.5,
                        10.5,
                        15.5
                    ],
                    "texture": "#0"
                },
                "up": {
                    "uv": [
                        9.5,
                        14.5,
                        10.5,
                        15.5
                    ],
                    "texture": "#0"
                },
                "down": {
                    "uv": [
                        9.5,
                        14.5,
                        10.5,
                        15.5
                    ],
                    "texture": "#0"
                }
            }
        },
        {
            "name": "bb_main2",
            "from": [
                5,
                2.5,
                3
            ],
            "to": [
                7,
                4.5,
                5
            ],
            "rotation": {
                "angle": 0,
                "axis": "y",
                "origin": [
                    8,
                    0,
                    8
                ]
            },
            "faces": {
                "north": {
                    "uv": [
                        11,
                        14.5,
                        12,
                        15.5
                    ],
                    "texture": "#0"
                },
                "east": {
                    "uv": [
                        11,
                        14.5,
                        12,
                        15.5
                    ],
                    "texture": "#0"
                },
                "south": {
                    "uv": [
                        11,
                        14.5,
                        12,
                        15.5
                    ],
                    "texture": "#0"
                },
                "west": {
                    "uv": [
                        11,
                        14.5,
                        12,
                        15.5
                    ],
                    "texture": "#0"
                },
                "up": {
                    "uv": [
                        11,
                        14.5,
                        12,
                        15.5
                    ],
                    "texture": "#0"
                },
                "down": {
                    "uv": [
                        11,
                        14.5,
                        12,
                        15.5
                    ],
                    "texture": "#0"
                }
            }
        },
        {
            "name": "bb_main2",
            "from": [
                3,
                3,
                6
            ],
            "to": [
                5,
                5,
                8
            ],
            "rotation": {
                "angle": 0,
                "axis": "y",
                "origin": [
                    8,
                    0,
                    8
                ]
            },
            "faces": {
                "north": {
                    "uv": [
                        11,
                        14.5,
                        12,
                        15.5
                    ],
                    "texture": "#0"
                },
                "east": {
                    "uv": [
                        11,
                        14.5,
                        12,
                        15.5
                    ],
                    "texture": "#0"
                },
                "south": {
                    "uv": [
                        11,
                        14.5,
                        12,
                        15.5
                    ],
                    "texture": "#0"
                },
                "west": {
                    "uv": [
                        11,
                        14.5,
                        12,
                        15.5
                    ],
                    "texture": "#0"
                },
                "up": {
                    "uv": [
                        11,
                        14.5,
                        12,
                        15.5
                    ],
                    "texture": "#0"
                },
                "down": {
                    "uv": [
                        11,
                        14.5,
                        12,
                        15.5
                    ],
                    "texture": "#0"
                }
            }
        },
        {
            "name": "bb_main2",
            "from": [
                9,
                5.25,
                10
            ],
            "to": [
                10,
                6.25,
                11
            ],
            "rotation": {
                "angle": 0,
                "axis": "y",
                "origin": [
                    8,
                    0,
                    8
                ]
            },
            "faces": {
                "north": {
                    "uv": [
                        8.5,
                        14.5,
                        9,
                        15
                    ],
                    "texture": "#0"
                },
                "east": {
                    "uv": [
                        8.5,
                        14.5,
                        9,
                        15
                    ],
                    "texture": "#0"
                },
                "south": {
                    "uv": [
                        8.5,
                        14.5,
                        9,
                        15
                    ],
                    "texture": "#0"
                },
                "west": {
                    "uv": [
                        8.5,
                        14.5,
                        9,
                        15
                    ],
                    "texture": "#0"
                },
                "up": {
                    "uv": [
                        8.5,
                        14.5,
                        9,
                        15
                    ],
                    "texture": "#0"
                },
                "down": {
                    "uv": [
                        8.5,
                        14.5,
                        9,
                        15
                    ],
                    "texture": "#0"
                }
            }
        },
        {
            "name": "bb_main2",
            "from": [
                6.25,
                4.5,
                5
            ],
            "to": [
                7.25,
                5.5,
                6
            ],
            "rotation": {
                "angle": 0,
                "axis": "y",
                "origin": [
                    8,
                    0,
                    8
                ]
            },
            "faces": {
                "north": {
                    "uv": [
                        8.5,
                        14.5,
                        9,
                        15
                    ],
                    "texture": "#0"
                },
                "east": {
                    "uv": [
                        8.5,
                        14.5,
                        9,
                        15
                    ],
                    "texture": "#0"
                },
                "south": {
                    "uv": [
                        8.5,
                        14.5,
                        9,
                        15
                    ],
                    "texture": "#0"
                },
                "west": {
                    "uv": [
                        8.5,
                        14.5,
                        9,
                        15
                    ],
                    "texture": "#0"
                },
                "up": {
                    "uv": [
                        8.5,
                        14.5,
                        9,
                        15
                    ],
                    "texture": "#0"
                },
                "down": {
                    "uv": [
                        8.5,
                        14.5,
                        9,
                        15
                    ],
                    "texture": "#0"
                }
            }
        },
        {
            "name": "bb_main2",
            "from": [
                4,
                5.5,
                7
            ],
            "to": [
                5,
                6.5,
                8
            ],
            "rotation": {
                "angle": 0,
                "axis": "y",
                "origin": [
                    8,
                    0,
                    8
                ]
            },
            "faces": {
                "north": {
                    "uv": [
                        8.5,
                        14.5,
                        9,
                        15
                    ],
                    "texture": "#0"
                },
                "east": {
                    "uv": [
                        8.5,
                        14.5,
                        9,
                        15
                    ],
                    "texture": "#0"
                },
                "south": {
                    "uv": [
                        8.5,
                        14.5,
                        9,
                        15
                    ],
                    "texture": "#0"
                },
                "west": {
                    "uv": [
                        8.5,
                        14.5,
                        9,
                        15
                    ],
                    "texture": "#0"
                },
                "up": {
                    "uv": [
                        8.5,
                        14.5,
                        9,
                        15
                    ],
                    "texture": "#0"
                },
                "down": {
                    "uv": [
                        8.5,
                        14.5,
                        9,
                        15
                    ],
                    "texture": "#0"
                }
            }
        },
        {
            "name": "bb_main2",
            "from": [
                3.5,
                3.5,
                11
            ],
            "to": [
                4.5,
                4.5,
                12
            ],
            "rotation": {
                "angle": 0,
                "axis": "y",
                "origin": [
                    8,
                    0,
                    8
                ]
            },
            "faces": {
                "north": {
                    "uv": [
                        8.5,
                        14.5,
                        9,
                        15
                    ],
                    "texture": "#0"
                },
                "east": {
                    "uv": [
                        8.5,
                        14.5,
                        9,
                        15
                    ],
                    "texture": "#0"
                },
                "south": {
                    "uv": [
                        8.5,
                        14.5,
                        9,
                        15
                    ],
                    "texture": "#0"
                },
                "west": {
                    "uv": [
                        8.5,
                        14.5,
                        9,
                        15
                    ],
                    "texture": "#0"
                },
                "up": {
                    "uv": [
                        8.5,
                        14.5,
                        9,
                        15
                    ],
                    "texture": "#0"
                },
                "down": {
                    "uv": [
                        8.5,
                        14.5,
                        9,
                        15
                    ],
                    "texture": "#0"
                }
            }
        },
        {
            "name": "bb_main2",
            "from": [
                11,
                4.5,
                3.5
            ],
            "to": [
                12,
                5.5,
                4.5
            ],
            "rotation": {
                "angle": 0,
                "axis": "y",
                "origin": [
                    8,
                    0,
                    8
                ]
            },
            "faces": {
                "north": {
                    "uv": [
                        8.5,
                        14.5,
                        9,
                        15
                    ],
                    "texture": "#0"
                },
                "east": {
                    "uv": [
                        8.5,
                        14.5,
                        9,
                        15
                    ],
                    "texture": "#0"
                },
                "south": {
                    "uv": [
                        8.5,
                        14.5,
                        9,
                        15
                    ],
                    "texture": "#0"
                },
                "west": {
                    "uv": [
                        8.5,
                        14.5,
                        9,
                        15
                    ],
                    "texture": "#0"
                },
                "up": {
                    "uv": [
                        8.5,
                        14.5,
                        9,
                        15
                    ],
                    "texture": "#0"
                },
                "down": {
                    "uv": [
                        8.5,
                        14.5,
                        9,
                        15
                    ],
                    "texture": "#0"
                }
            }
        },
        {
            "name": "bb_main2",
            "from": [
                9.75,
                3.75,
                6.75
            ],
            "to": [
                10.75,
                4.75,
                7.75
            ],
            "rotation": {
                "angle": 0,
                "axis": "y",
                "origin": [
                    8,
                    0,
                    8
                ]
            },
            "faces": {
                "north": {
                    "uv": [
                        8.5,
                        14.5,
                        9,
                        15
                    ],
                    "texture": "#0"
                },
                "east": {
                    "uv": [
                        8.5,
                        14.5,
                        9,
                        15
                    ],
                    "texture": "#0"
                },
                "south": {
                    "uv": [
                        8.5,
                        14.5,
                        9,
                        15
                    ],
                    "texture": "#0"
                },
                "west": {
                    "uv": [
                        8.5,
                        14.5,
                        9,
                        15
                    ],
                    "texture": "#0"
                },
                "up": {
                    "uv": [
                        8.5,
                        14.5,
                        9,
                        15
                    ],
                    "texture": "#0"
                },
                "down": {
                    "uv": [
                        8.5,
                        14.5,
                        9,
                        15
                    ],
                    "texture": "#0"
                }
            }
        },
        {
            "name": "bb_main2",
            "from": [
                6,
                3,
                11
            ],
            "to": [
                8,
                5,
                13
            ],
            "rotation": {
                "angle": 0,
                "axis": "y",
                "origin": [
                    8,
                    0,
                    8
                ]
            },
            "faces": {
                "north": {
                    "uv": [
                        11,
                        14.5,
                        12,
                        15.5
                    ],
                    "texture": "#0"
                },
                "east": {
                    "uv": [
                        11,
                        14.5,
                        12,
                        15.5
                    ],
                    "texture": "#0"
                },
                "south": {
                    "uv": [
                        11,
                        14.5,
                        12,
                        15.5
                    ],
                    "texture": "#0"
                },
                "west": {
                    "uv": [
                        11,
                        14.5,
                        12,
                        15.5
                    ],
                    "texture": "#0"
                },
                "up": {
                    "uv": [
                        11,
                        14.5,
                        12,
                        15.5
                    ],
                    "texture": "#0"
                },
                "down": {
                    "uv": [
                        11,
                        14.5,
                        12,
                        15.5
                    ],
                    "texture": "#0"
                }
            }
        },
        {
            "name": "bb_main2",
            "from": [
                11,
                3,
                4
            ],
            "to": [
                13,
                5,
                6
            ],
            "rotation": {
                "angle": 0,
                "axis": "y",
                "origin": [
                    8,
                    0,
                    8
                ]
            },
            "faces": {
                "north": {
                    "uv": [
                        9.5,
                        14.5,
                        10.5,
                        15.5
                    ],
                    "texture": "#0"
                },
                "east": {
                    "uv": [
                        9.5,
                        14.5,
                        10.5,
                        15.5
                    ],
                    "texture": "#0"
                },
                "south": {
                    "uv": [
                        9.5,
                        14.5,
                        10.5,
                        15.5
                    ],
                    "texture": "#0"
                },
                "west": {
                    "uv": [
                        9.5,
                        14.5,
                        10.5,
                        15.5
                    ],
                    "texture": "#0"
                },
                "up": {
                    "uv": [
                        9.5,
                        14.5,
                        10.5,
                        15.5
                    ],
                    "texture": "#0"
                },
                "down": {
                    "uv": [
                        9.5,
                        14.5,
                        10.5,
                        15.5
                    ],
                    "texture": "#0"
                }
            }
        },
        {
            "name": "bb_main2",
            "from": [
                11,
                2.7,
                8
            ],
            "to": [
                13,
                4.7,
                10
            ],
            "rotation": {
                "angle": 0,
                "axis": "y",
                "origin": [
                    8,
                    0,
                    8
                ]
            },
            "faces": {
                "north": {
                    "uv": [
                        11,
                        14.5,
                        12,
                        15.5
                    ],
                    "texture": "#0"
                },
                "east": {
                    "uv": [
                        11,
                        14.5,
                        12,
                        15.5
                    ],
                    "texture": "#0"
                },
                "south": {
                    "uv": [
                        11,
                        14.5,
                        12,
                        15.5
                    ],
                    "texture": "#0"
                },
                "west": {
                    "uv": [
                        11,
                        14.5,
                        12,
                        15.5
                    ],
                    "texture": "#0"
                },
                "up": {
                    "uv": [
                        11,
                        14.5,
                        12,
                        15.5
                    ],
                    "texture": "#0"
                },
                "down": {
                    "uv": [
                        11,
                        14.5,
                        12,
                        15.5
                    ],
                    "texture": "#0"
                }
            }
        }
    ],
    "groups": [
        {
            "name": "bb_main2",
            "origin": [
                8,
                0,
                8
            ],
            "color": 0,
            "children": [
                0,
                1,
                2,
                3,
                4,
                5,
                6,
                7,
                8,
                9,
                10,
                11,
                12,
                13,
                14,
                15,
                16,
                17,
                18
            ]
        }
    ]
}